main.py
setup.py
ImageDream.egg-info/PKG-INFO
ImageDream.egg-info/SOURCES.txt
ImageDream.egg-info/dependency_links.txt
ImageDream.egg-info/requires.txt
ImageDream.egg-info/top_level.txt